cusrl/__init__.py
cusrl/__main__.py
cusrl/cli/__init__.py
cusrl/cli/export.py
cusrl/cli/list_experiments.py
cusrl/cli/play.py
cusrl/cli/train.py
cusrl/cli/utils.py
cusrl/environment/__init__.py
cusrl/environment/gym.py
cusrl/environment/isaaclab.py
cusrl/hook/__init__.py
cusrl/hook/advantage.py
cusrl/hook/amp.py
cusrl/hook/condition.py
cusrl/hook/distillation.py
cusrl/hook/environment_spec.py
cusrl/hook/gae.py
cusrl/hook/gradient.py
cusrl/hook/initialization.py
cusrl/hook/lr_schedule.py
cusrl/hook/normalization.py
cusrl/hook/on_policy.py
cusrl/hook/ppo.py
cusrl/hook/representation.py
cusrl/hook/reward.py
cusrl/hook/rnd.py
cusrl/hook/schedule.py
cusrl/hook/smoothness.py
cusrl/hook/symmetry.py
cusrl/hook/value.py
cusrl/logger/__init__.py
cusrl/logger/swanlab_logger.py
cusrl/logger/tensorboard_logger.py
cusrl/logger/wandb_logger.py
cusrl/module/__init__.py
cusrl/module/activation.py
cusrl/module/actor.py
cusrl/module/bijector.py
cusrl/module/causal_attn.py
cusrl/module/cnn.py
cusrl/module/critic.py
cusrl/module/detach_grad.py
cusrl/module/distribution.py
cusrl/module/export.py
cusrl/module/gate.py
cusrl/module/inference.py
cusrl/module/mha.py
cusrl/module/mlp.py
cusrl/module/module.py
cusrl/module/normal_nll_loss.py
cusrl/module/normalization.py
cusrl/module/normalizer.py
cusrl/module/parameter.py
cusrl/module/rnn.py
cusrl/module/sequential.py
cusrl/module/simba.py
cusrl/module/stub.py
cusrl/module/transformer.py
cusrl/preset/__init__.py
cusrl/preset/amp.py
cusrl/preset/distillation.py
cusrl/preset/ppo.py
cusrl/sampler/__init__.py
cusrl/sampler/mini_batch_sampler.py
cusrl/sampler/random_sampler.py
cusrl/template/__init__.py
cusrl/template/actor_critic.py
cusrl/template/agent.py
cusrl/template/buffer.py
cusrl/template/environment.py
cusrl/template/hook.py
cusrl/template/logger.py
cusrl/template/optimizer.py
cusrl/template/player.py
cusrl/template/trainer.py
cusrl/template/trial.py
cusrl/utils/__init__.py
cusrl/utils/config.py
cusrl/utils/dict_utils.py
cusrl-1.1.5.dist-info/licenses/LICENSE
cusrl-1.1.5.dist-info/METADATA
cusrl-1.1.5.dist-info/WHEEL
cusrl-1.1.5.dist-info/top_level.txt
cusrl-1.1.5.dist-info/RECORD
