Metadata-Version: 2.4
Name: cusrl
Version: 1.1.5
Summary: Customizable and modular RL algorithms implemented in PyTorch
Author-email: Chengrui Zhu <jewel@zju.edu.cn>
Keywords: reinforcement-learning,pytorch,rl
Requires-Python: >=3.10
License-File: LICENSE
Requires-Dist: gitpython~=3.1.44
Requires-Dist: gymnasium>=1.1.0
Requires-Dist: numpy>=1.26.0
Requires-Dist: objprint~=0.3.0
Requires-Dist: pyyaml~=6.0.2
Requires-Dist: torch>=2.4.0
Provides-Extra: dev
Requires-Dist: cusrl[all]; extra == "dev"
Requires-Dist: pre-commit; extra == "dev"
Requires-Dist: pytest; extra == "dev"
Provides-Extra: export
Requires-Dist: onnx; extra == "export"
Requires-Dist: onnxruntime; extra == "export"
Requires-Dist: onnxscript; extra == "export"
Requires-Dist: onnxslim!=v0.1.62; extra == "export"
Provides-Extra: swanlab
Requires-Dist: swanlab; extra == "swanlab"
Provides-Extra: tensorboard
Requires-Dist: tensorboard; extra == "tensorboard"
Provides-Extra: wandb
Requires-Dist: wandb; extra == "wandb"
Provides-Extra: all
Requires-Dist: cusrl[export,swanlab,tensorboard,wandb]; extra == "all"
Dynamic: license-file
